pyWAppSel/Client.py
pyWAppSel/__init__.py
pyWAppSel/browser.py
pyWAppSel/elements.py
pyWAppSel/types.py
pyWAppSel-1.0.5.dist-info/LICENSE
pyWAppSel-1.0.5.dist-info/METADATA
pyWAppSel-1.0.5.dist-info/NOTICE
pyWAppSel-1.0.5.dist-info/WHEEL
pyWAppSel-1.0.5.dist-info/top_level.txt
pyWAppSel-1.0.5.dist-info/RECORD
