Metadata-Version: 2.1
Name: pyWAppSel
Version: 1.0.5
Summary: pyWAppSel is a selenium-based Whatsapp wrapper
Home-page: https://github.com/pysashapy/pyWApp
Author: Dark White
Author-email: sasha.2000ibr@gmail.com
License: Apache License 2.0
Platform: UNKNOWN
Classifier: Programming Language :: Python :: 3.10
Classifier: Operating System :: OS Independent
Requires-Python: >=3.6
License-File: LICENSE
License-File: NOTICE
Requires-Dist: selenium
Requires-Dist: webdriver-manager
